pyerf/__about__.py
pyerf/__init__.py
pyerf/pyerf.py
pyerf/tests/__init__.py
pyerf/tests/test_pyerf.py
pyerf-1.0.1.dist-info/DESCRIPTION.rst
pyerf-1.0.1.dist-info/METADATA
pyerf-1.0.1.dist-info/RECORD
pyerf-1.0.1.dist-info/WHEEL
pyerf-1.0.1.dist-info/metadata.json
pyerf-1.0.1.dist-info/top_level.txt
